synrfp/__init__.py
synrfp/encoder.py
synrfp/synrfp.py
synrfp/graph/__init__.py
synrfp/graph/graph_data.py
synrfp/graph/reaction.py
synrfp/sketchers/__init__.py
synrfp/sketchers/base.py
synrfp/sketchers/cw_sketch.py
synrfp/sketchers/minhash_sketch.py
synrfp/sketchers/parity_fold.py
synrfp/tokenizers/__init__.py
synrfp/tokenizers/base.py
synrfp/tokenizers/nauty.py
synrfp/tokenizers/utils.py
synrfp/tokenizers/wl.py
synrfp-0.0.1.dist-info/METADATA
synrfp-0.0.1.dist-info/WHEEL
synrfp-0.0.1.dist-info/licenses/LICENSE
synrfp-0.0.1.dist-info/RECORD
