Metadata-Version: 2.4
Name: synrfp
Version: 0.0.1
Summary: Reaction fingerprint
Project-URL: homepage, https://github.com/TieuLongPhan/synrfp
Project-URL: source, https://github.com/TieuLongPhan/synrfp
Project-URL: issues, https://github.com/TieuLongPhan/synrfp/issues
Project-URL: documentation, https://synrfp.readthedocs.io/en/latest/
Author-email: Tieu Long Phan <tieu@bioinf.uni-leipzig.de>
License-File: LICENSE
Classifier: License :: OSI Approved :: MIT License
Classifier: Operating System :: OS Independent
Classifier: Programming Language :: Python :: 3
Requires-Python: >=3.11
Requires-Dist: datasketch>=1.6.5
Requires-Dist: pynauty>=2.8.8.1
Requires-Dist: synkit>=0.0.13
Provides-Extra: all
Requires-Dist: numpy>=2.2.0; extra == 'all'
Requires-Dist: pandas>=1.5.3; extra == 'all'
Provides-Extra: docs
Requires-Dist: sphinx-rtd-theme; extra == 'docs'
Requires-Dist: sphinx>=6.0; extra == 'docs'
Requires-Dist: sphinxcontrib-bibtex; extra == 'docs'
